{
  "nom": "jjayyfeather",
  "signupDate": "2016-08-04T05:46:38.759Z",
  "curClass": "PyroKinetic",
  "curBranch": "Archer",
  "curWeap": "Shortbow",
  "classLvl": {
    "cyrokinesis": 1,
    "pyrokinetic": 2,
    "skirmisher": 1,
    "guardian": 1,
    "bard": 1
  },
  "branchLvl": {
    "dueler": 1,
    "heavy": 1,
    "archer": 3,
    "sorcerer": 1,
    "fighter": 1
  },
  "xp": 9,
  "infraction": {
    "gameban": false,
    "gbReason": "",
    "gbLength": "",
    "hostban": false,
    "hbReason": "",
    "hbLength": ""
  },
  "battle": false
}